mcp_macos/__init__.py
mcp_macos/main.py
mcp_macos/scripts/cal_create_event_at.applescript
mcp_macos/scripts/cal_list_next_events.applescript
mcp_macos/scripts/mail_get_email_by_id.applescript
mcp_macos/scripts/mail_list_accounts.applescript
mcp_macos/scripts/mail_list_emails.applescript
mcp_macos/scripts/mail_list_mailboxes.applescript
mcp_macos/scripts/mail_list_unread.applescript
mcp_macos/scripts/mail_send.applescript
mcp_macos/scripts/mail_unread_inbox_count.applescript
mcp_macos/scripts/mail_update_email_status.applescript
mcp_macos/servers/__init__.py
mcp_macos/servers/calendar.py
mcp_macos/servers/mail.py
mcp_macos/utils.py
mcp_macos-0.3.0.dist-info/WHEEL
mcp_macos-0.3.0.dist-info/entry_points.txt
mcp_macos-0.3.0.dist-info/METADATA
mcp_macos-0.3.0.dist-info/RECORD
